pipexlosspython/__init__.py
pipexlosspython/losses.py
pipexlosspython-0.1.1.dist-info/METADATA
pipexlosspython-0.1.1.dist-info/WHEEL
pipexlosspython-0.1.1.dist-info/top_level.txt
pipexlosspython-0.1.1.dist-info/RECORD
