Metadata-Version: 2.4
Name: PipexLossPython
Version: 0.1.1
Summary: A PyTorch loss package with log-cosh and PIPEX loss
Author-email: Your Name <you@example.com>
License: Rasmus Börjesson Dahlstedt
Project-URL: Homepage, https://github.com/yourusername/pipexloss
Requires-Python: >=3.7
Requires-Dist: torch>=1.8
Requires-Dist: pytorch-msssim
